codeforces_api/__init__.py
codeforces_api/api_request_maker.py
codeforces_api/api_requests.py
codeforces_api/parse_methods.py
codeforces_api/types.py
codeforces_api/version.py
CodeforcesApiPy-2.0.12.dist-info/LICENSE
CodeforcesApiPy-2.0.12.dist-info/METADATA
CodeforcesApiPy-2.0.12.dist-info/WHEEL
CodeforcesApiPy-2.0.12.dist-info/top_level.txt
CodeforcesApiPy-2.0.12.dist-info/RECORD
