Metadata-Version: 2.1
Name: CodeforcesApiPy
Version: 2.0.12
Summary: Implementation of codeforces.com API
Home-page: https://github.com/VadVergasov/CodeforcesApiPy
Author: VadVergasov
Author-email: vadim.vergasov2003@gmail.com
License: GPLv3
Keywords: codeforces api python
Platform: any
Classifier: Programming Language :: Python :: 3
Classifier: License :: OSI Approved :: GNU General Public License v3 (GPLv3)
Classifier: Operating System :: OS Independent
Requires-Python: >=3.8
License-File: LICENSE
Requires-Dist: requests
Requires-Dist: lxml
